tmorse/__init__.py
tmorse/__main__.py
tmorse/args.py
tmorse/data/codes.json
tmorse-0.1.7.dist-info/entry_points.txt
tmorse-0.1.7.dist-info/LICENSE
tmorse-0.1.7.dist-info/WHEEL
tmorse-0.1.7.dist-info/METADATA
tmorse-0.1.7.dist-info/RECORD
