Metadata-Version: 2.1
Name: tmorse
Version: 0.1.7
Summary: Blinking Morse code on Thinkpad LEDs
Home-page: https://github.com/mahyar24/TMorse/
License: GPLv3
Author: Mahyar Mahdavi
Author-email: Mahyar@Mahyar24.com
Requires-Python: >=3.9,<4.0
Classifier: License :: Other/Proprietary License
Classifier: Programming Language :: Python :: 3
Classifier: Programming Language :: Python :: 3.10
Classifier: Programming Language :: Python :: 3.9
Project-URL: Repository, https://github.com/mahyar24/TMorse/
